Workbook

Sheet Registro
A1: FECHA | B1: VENDEDOR | C1: ZONA | D1: CLIENTE | E1: N° CLIENTE | F1: DNI | G1: TELEFONO | H1: LOCALIDAD | I1: PRODUCTOS | J1: PLANES | K1: ANTICIPO | L1: TOTAL | M1: CONYUGUE | N1: DNI CONYUGUE | O1: TEL CONYUGUE | P1: OBSERVACIONES | Q1: DNIS CONIGUALES
A2: 46010.852 | B2: SEBASTIAN | C2: CATAMARCA | D2: LUJAN MARIA LAURA | F2: 34783489 | G2: 3834190133 | H2: CATAMARCA | I2: [31335] VITRINA EXPOSITORA FAM 520LTS 198CM X 71.5CM | J2: 46 SEMANAS (46 de $60.000) (ESPECIAL/OFERTA) | K2: $ 60.000 | L2: $2.760.000 | M2: PACHECO MIGUEL | N2: 32698148 | Q2: =IF(N2="", "", IF(COUNTIF(F:F, N2)>0, "⚠️ ERROR: YA ES TITULAR", ""))
A3: 46011.419 | B3: RACHID TURBAY | C3: LOS ALTOS | D3: GUARAZ JUAN CARLOS | F3: 20714826 | G3: 3834517687 | H3: BAÑADO DE OVANTA | I3: [31835] CONSERVADORA PARA HELADOS FAM 220LTS TAPA DE CRISTAL CURVO | J3: 33 SEMANAS (33 de $44.000) (ESPECIAL/OFERTA) | K3: $ 44.000 | L3: $1.452.000 | M3: COLLANTE LUCIANA | N3: 29104369 | P3: Venta por cambio. | Q3: =IF(N3="", "", IF(COUNTIF(F:F, N3)>0, "⚠️ ERROR: YA ES TITULAR", ""))
A4: 46011.488 | B4: ARIAS JENNIFER | C4: CONCEPCIÓN | D4: FIGUEROA HUMBERTO | F4: 27141564 | G4: 3865672557 | H4: CONCEPCIÓN | I4: [30500] VENTILADOR DE PARED CRIVEL 30" V40 INDUSTRIAL | J4: 12 SEMANAS (12 de $25.600) | K4: $ 25.600 | L4: $307.200 | M4: ANA LIA ALBORADO | N4: 31312339 | P4: Esta a partir de las 10 a 15 | Q4: =IF(N4="", "", IF(COUNTIF(F:F, N4)>0, "⚠️ ERROR: YA ES TITULAR", ""))
A5: 46011.498 | B5: SOLANA | C5: CATAMARCA | D5: BRIZUELA CRISTINA ALILIA | F5: 22219976 | G5: 3834303788 | H5: CATAMARCA | I5: [32215] SOMMIER MAXIKIG DE 2 1/2 ESPUMA 30CM ZAFIRO | J5: CONTADO ($572.300) | K5: $ 572.300 | L5: $572.300 | Q5: =IF(N5="", "", IF(COUNTIF(F:F, N5)>0, "⚠️ ERROR: YA ES TITULAR", ""))
A6: 46011.622 | B6: JOHN | C6: SUR CATAMARCA | D6: CARRIZO FABIANA MARISEL | F6: 32851577 | G6: 3834012088 | H6: CAPITAL CATAMARCA | I6: [32223] CELULAR REDMI 15C CON 16RAM Y 256GB | J6: 24 SEMANAS (24 de $26.600) | K6: $ 26.600 | L6: $638.400 | M6: MORALES JUAN ADRIAN | N6: 34187127 | P6: Polleria Noah | Q6: =IF(N6="", "", IF(COUNTIF(F:F, N6)>0, "⚠️ ERROR: YA ES TITULAR", ""))
A7: 46011.835 | B7: RACHID | C7: ALBERDI | D7: BRIZUELA VALENTINA | F7: 45669557 | G7: 3814189518 | H7: ALBERDI | I7: [31580] SIERRA CARNICERA MOD.320 MONOFASICA 2HP MESADA DE AC. INX. | J7: 33 SEMANAS (33 de $137.900) | K7: $ 137.900 | L7: $4.550.700 | M7: ALBARRACIN ISAIAS | N7: 45125190 | Q7: =IF(N7="", "", IF(COUNTIF(F:F, N7)>0, "⚠️ ERROR: YA ES TITULAR", ""))
A8: 46012.962 | B8: JUAN MONTEROS | C8: CONCEPCIÓN | D8: CEJAS ESTER | F8: 18300841 | G8: 3865290520 | H8: ALTO VERDE | I8: [31948] LICUADORA LITIUM 1.5LTS VASO VIDRIO/500W/ 5 VEL /PICA HIELO | J8: 6 SEMANAS (6 de $25.000) (ESPECIAL/OFERTA) | K8: $ 25.000 | L8: $150.000 | M8: CEJAS JOEL | N8: 42717595 | Q8: =IF(N8="", "", IF(COUNTIF(F:F, N8)>0, "⚠️ ERROR: YA ES TITULAR", ""))
A9: 46013.38 | B9: RUBEN | C9: FAMAILLA | D9: RUBÉN MAMANI | F9: 29048976 | G9: 3815112636 | H9: FAMAILLA | I9: [32011] AIRE ACONDICIONADO SPLIT ALASKA 3550W DE 3000 FRIG. F/CALOR | J9: 33 SEMANAS (33 de $64.600) | K9: $ 64.600 | L9: $2.131.800 | M9: CASTRO JULIA | N9: 31770372 | P9: Horario comercial 8 a 14 | Q9: =IF(N9="", "", IF(COUNTIF(F:F, N9)>0, "⚠️ ERROR: YA ES TITULAR", ""))
A10: 46013.41 | B10: FRANCO | C10: MOLLAR-TAFI | D10: GRIMALT KAREN LUCIA | F10: 40028787 | G10: 3815620884 | H10: TAFI DEL VALLE | I10: [31912] MUEBLES DE 15 CUBOS MDF DE 1MTSX.45CMX1.85MTS | J10: 33 SEMANAS (33 de $21.200) | K10: $ 21.200 | L10: $699.600 | M10: CEQUEIRA FACUNDO ADRIAN | N10: 41184528 | Q10: =IF(N10="", "", IF(COUNTIF(F:F, N10)>0, "⚠️ ERROR: YA ES TITULAR", ""))
A11: 46013.426 | B11: CHAILE | C11: MONTEROS | D11: JOSÉ JAVIER GOMEZ | F11: 41447476 | G11: 3812109862 | H11: BELLA VISTA | I11: [31719] MOSTRADOR MULTIFUNCION MT 1.50MTS X 0.45CM MDF CAR. Y CAJON | J11: 33 SEMANAS (33 de $21.300) | K11: $ 21.300 | L11: $702.900 | M11: LORENA PAOLA JUAREZ | N11: 40086992 | Q11: =IF(N11="", "", IF(COUNTIF(F:F, N11)>0, "⚠️ ERROR: YA ES TITULAR", ""))
A12: 46013.496 | B12: ELSA | C12: SUR | D12: BRUNELLO, VALENTINA | F12: 44117256 | G12: 3834594447 | H12: VALLE CHICO | I12: [32024] HORNO PIZZERO CATANIA 6M PUERTA DE VIDRIO C/CALIENTA PLATOS | J12: 24 SEMANAS (24 de $49.100) | K12: $ 49.100 | L12: $1.178.400 | M12: BRANCIA, CINTIA | N12: 34777837 | Q12: =IF(N12="", "", IF(COUNTIF(F:F, N12)>0, "⚠️ ERROR: YA ES TITULAR", ""))
A13: 46013.503 | B13: ELSA | C13: CATAMARCA | D13: GUZMAN, SANDRA DEL VALLE | F13: 18060901 | G13: 3834380773 | H13: CATAMARCA | I13: [302] HORNO PIZZERO TECNOCALOR 12 MOLDES AC/INOX GE INDUSTRIAL | J13: 33 SEMANAS (33 de $47.000) | K13: $ 47.000 | L13: $1.551.000 | M13: FERREYRA VERONICA YANEL | N13: 36844813 | Q13: =IF(N13="", "", IF(COUNTIF(F:F, N13)>0, "⚠️ ERROR: YA ES TITULAR", ""))
A14: 46013.517 | B14: ELSA | C14: SUR | D14: QUINTEROS, ADRIEL ANTONIO | F14: 29651136 | G14: 3834325939 | H14: MIRAFLORES | I14: [32177] LOMITERA CON CARLITERA DEPAOLO DE 60X80 | J14: 33 SEMANAS (33 de $37.600) | K14: $ 37.600 | L14: $1.240.800 | M14: ARREGUEZ, ANA BELEN | N14: 34803916 | P14: Frente al Correo | Q14: =IF(N14="", "", IF(COUNTIF(F:F, N14)>0, "⚠️ ERROR: YA ES TITULAR", ""))
A15: 46013.639 | B15: MARIANO | C15: CONCEPCIÓN | D15: JOTALLAN MANUEL | F15: 40700471 | G15: 3865229087 | H15: CONCEPCIÓN | I15: [32223] CELULAR REDMI 15C CON 16RAM Y 256GB | J15: 33 SEMANAS (33 de $19.800) | K15: $ 19.800 | L15: $653.400 | M15: JOTALLAN ANA | N15: 11007704 | Q15: =IF(N15="", "", IF(COUNTIF(F:F, N15)>0, "⚠️ ERROR: YA ES TITULAR", ""))
A16: 46013.766 | B16: SARMIENTO JONATHAN | C16: CATAMARCA | D16: CISTERNAS ANDREA BETSABET | F16: 27547644 | G16: 3834054136 | H16: VILLA DOLORES | I16: [31708] AMASADORA INDUSTRIAL DE 20KG MARTINO | J16: 48 SEMANAS (48 de $45.600) | K16: $ 45.600 | L16: $2.188.800 | M16: STELLA MARIS CISTERNAS | N16: 29369429 | Q16: =IF(N16="", "", IF(COUNTIF(F:F, N16)>0, "⚠️ ERROR: YA ES TITULAR", ""))
A17: 46013.772 | B17: RUBEN | C17: LULES(MERCED) | D17: JUAREZ SEBASTIÁN AUGUSTO | F17: 27578510 | G17: 3813305224 | H17: LULES | I17: [32139] FREIDORA DE AIRE LÜSQTOFF DE 9.5 LTS DE 1800W | J17: 12 SEMANAS (12 de $29.300) | K17: $ 29.300 | L17: $351.600 | M17: JUAREZ MARISEL | N17: 31808922 | P17: Nota ya autorizada , cambio de producto | Q17: =IF(N17="", "", IF(COUNTIF(F:F, N17)>0, "⚠️ ERROR: YA ES TITULAR", ""))
A18: 46013.82 | B18: SEBASTIAN | C18: CONCEPCION | D18: ALBORNOZ PEDRO NICOLAS | F18: 28919912 | G18: 3865749898 | H18: CONCEPCION | I18: [30918] KIOSCO INTEGRAL FRENTE DE VIDRIO 1.80 X 0.45CM MDF [32150] BATIDORA MOULINEX COLOR NEGRO 3.2LTS 500W 5 VEL | J18: 1 SEMANAS (1 de $377.100) (ESPECIAL/OFERTA) 1 SEMANAS (1 de $118.380) (ESPECIAL/OFERTA) | K18: $ 495.480 | L18: $377.100 $118.380 | Q18: =IF(N18="", "", IF(COUNTIF(F:F, N18)>0, "⚠️ ERROR: YA ES TITULAR", ""))
A19: 46014.009 | B19: MARIANO | C19: ALBERDI | D19: GAMBARTE OLGA | F19: 20334003 | G19: 3865327894 | H19: LA COCHA | I19: [15] COMBO DE PRODUCTOS [32092] CARLITERA SIMPLE DANDA MULTIGAS C/ VALVULA DE SEGURIDAD [30747] FREIDOR COMERCIAL TECNOC. 18 LTS LINEA ECONOMICA [130] CORTAPAPAS VERTICAL NATIVA A BASTON CON TRES MOLDES | J19: 42 SEMANAS (42 de $36.500) (ESPECIAL/OFERTA) 0 SEMANAS (0 de $0) (ESPECIAL/OFERTA) 0 SEMANAS (0 de $0) (ESPECIAL/OFERTA) 0 SEMANAS (0 de $0) (ESPECIAL/OFERTA) | K19: $ 36.500 | L19: $1.533.000 $0 $0 $0 | M19: SALINAS NOELIA | N19: 33490809 | Q19: =IF(N19="", "", IF(COUNTIF(F:F, N19)>0, "⚠️ ERROR: YA ES TITULAR", ""))
A20: 46014.423 | B20: SEBASTIAN | C20: CONCEPCION | D20: FLORES MIRTA | F20: 30998597 | G20: 3865373159 | H20: ALPACHIRI | I20: [31240] MOSTRADOR DE 0.90X1.85X0.45 CON ESTANTES Y PUERTAS CORREDIZA | J20: 1 SEMANAS (1 de $428.100) (ESPECIAL/OFERTA) | K20: $ 428.100 | L20: $428.100 | P20: Venta con tarjeta | Q20: =IF(N20="", "", IF(COUNTIF(F:F, N20)>0, "⚠️ ERROR: YA ES TITULAR", ""))
A21: 46014.434 | B21: RACHID | C21: TACO RALO | D21: ONTIVERO PATRICIA | F21: 17937748 | G21: 3816260106 | H21: SAN PEDRO | I21: [31335] VITRINA EXPOSITORA FAM 520LTS 198CM X 71.5CM | J21: 46 SEMANAS (46 de $60.000) (ESPECIAL/OFERTA) | K21: $ 60.000 | L21: $2.760.000 | M21: MORENO NATALIA | N21: 36041046 | Q21: =IF(N21="", "", IF(COUNTIF(F:F, N21)>0, "⚠️ ERROR: YA ES TITULAR", ""))
A22: 46014.437 | B22: RUBÉN MAMANI | C22: LULES | D22: CHINCHA EUGENIA | F22: 92614054 | G22: 3815605991 | H22: LULES (MERCED) | I22: [31237] VITRINA DOBLE MT 1.85MTS X 0.90 X 0.45CM MDF C/PUERTAS | J22: 24 SEMANAS (24 de $25.800) | K22: $ 25.800 | L22: $619.200 | M22: CHINCHA MARIVEL | N22: 92760508 | P22: Av roca 1000 | Q22: =IF(N22="", "", IF(COUNTIF(F:F, N22)>0, "⚠️ ERROR: YA ES TITULAR", ""))
A23: 46014.761 | B23: RACHID | C23: LOS ALTOS | D23: DIAZ JANET | F23: 44688478 | G23: 3834975007 | H23: LOS ALTOS | I23: [31335] VITRINA EXPOSITORA FAM 520LTS 198CM X 71.5CM | J23: 46 SEMANAS (46 de $60.000) (ESPECIAL/OFERTA) | K23: $ 60.000 | L23: $2.760.000 | M23: DIAZ CHRISTIAN | N23: 26244717 | Q23: =IF(N23="", "", IF(COUNTIF(F:F, N23)>0, "⚠️ ERROR: YA ES TITULAR", ""))
A24: 46014.794 | B24: BALTIERRA DANIEL | C24: ANDALGALA | D24: LÓPEZ SAACHET EMANUEL | F24: 32628878 | G24: 3835488112 | H24: ANDALGALA | I24: [32179] CORTADORA DE FIAMBRES BIANCHI 330 TRANSMISION A CORREA | J24: 12 SEMANAS (12 de $175.200) | K24: $ 175.200 | L24: $2.102.400 | M24: LÓPEZ RENÉ | N24: 11682746 | P24: Frente plaza principal | Q24: =IF(N24="", "", IF(COUNTIF(F:F, N24)>0, "⚠️ ERROR: YA ES TITULAR", ""))
A25: 46015.386 | B25: NELSON | C25: ZONA SUR | D25: SOSA SERGIO | F25: 35501150 | G25: 3834066850 | H25: CATAMARCA | I25: [31213] PLACARD 6 PUERTAS 2 CAJONES FERRO MUEBLES-C/CEDRO [30297] JUEGO DE COMEDOR SALUMA 1.80X80+6 SILLAS IMPERIAL/RESP/ALTO | J25: 36 SEMANAS (36 de $45.500) (ESPECIAL/OFERTA) | K25: $ 45.500 | L25: $1.638.000 - | M25: HERRERA CLARA | N25: 39806582 | Q25: =IF(N25="", "", IF(COUNTIF(F:F, N25)>0, "⚠️ ERROR: YA ES TITULAR", ""))
A26: 46015.388 | B26: NELSON | C26: ZONA SUR | D26: SOSA SERGIO | F26: 35501150 | G26: 3834066850 | H26: CATAMARCA | I26: [31213] PLACARD 6 PUERTAS 2 CAJONES FERRO MUEBLES-C/CEDRO [30297] JUEGO DE COMEDOR SALUMA 1.80X80+6 SILLAS IMPERIAL/RESP/ALTO | J26: 36 SEMANAS (36 de $45.500) (ESPECIAL/OFERTA) A DEFINIR | K26: $ 45.500 | L26: $1.638.000 - | M26: HERRERA CLARA | N26: 39806582 | Q26: =IF(N26="", "", IF(COUNTIF(F:F, N26)>0, "⚠️ ERROR: YA ES TITULAR", ""))
A27: 46015.43 | B27: SARMIENTO JONATHAN | C27: CATAMARCA | D27: SARMIENTO JONATHAN LEANDRO | F27: 35208752 | G27: 3834805370 | H27: FRAY MAMERTO ESQUIU | I27: [32215] SOMMIER MAXIKIG DE 2 1/2 ESPUMA 30CM ZAFIRO | J27: CONTADO ($572.300) | K27: $ 572.300 | L27: $572.300 | M27: ZURITA ANAHI | N27: 34187583 | Q27: =IF(N27="", "", IF(COUNTIF(F:F, N27)>0, "⚠️ ERROR: YA ES TITULAR", ""))
A28: 46015.482 | B28: NELSON | C28: ZONA SUR | D28: AYBAR BRAIAN EMIR | F28: 47837792 | G28: 3834222151 | H28: CATAMARCA | I28: [1] BALANZA ELECTRONICA KRETZ NOVEL ECO2 30KG C/BAT CONTADORA | J28: 24 SEMANAS (24 de $25.000) | K28: $ 25.000 | L28: $600.000 | M28: SALINAS DÉBORA JESSICA | N28: 33670479 | Q28: =IF(N28="", "", IF(COUNTIF(F:F, N28)>0, "⚠️ ERROR: YA ES TITULAR", ""))
A29: 46015.484 | B29: RACHID | C29: TACO RALO | D29: MARQUEZ MARTA | F29: 23655273 | G29: 3813621736 | H29: EL ALTO | I29: [32010] PILETA DE NATACION PELOPINCHO DE 8000LTS 4.50X2.25X0.80ALTO | J29: 48 SEMANAS (48 de $18.700) | K29: $ 18.700 | L29: $897.600 | M29: AREVALO JULIO RAUL | N29: 20595181 | Q29: =IF(N29="", "", IF(COUNTIF(F:F, N29)>0, "⚠️ ERROR: YA ES TITULAR", ""))
A30: 46015.484 | B30: RACHID | C30: TACO RALO | D30: MARQUEZ MARTA | F30: 23655273 | G30: 3813621736 | H30: EL ALTO | I30: [32010] PILETA DE NATACION PELOPINCHO DE 8000LTS 4.50X2.25X0.80ALTO | J30: 48 SEMANAS (48 de $18.700) | K30: $ 18.700 | L30: $897.600 | M30: AREVALO JULIO RAUL | N30: 20595181 | Q30: =IF(N30="", "", IF(COUNTIF(F:F, N30)>0, "⚠️ ERROR: YA ES TITULAR", ""))
A31: 46015.507 | B31: IBAÑEZ ENRIQUE | C31: TRINIDAD | D31: CABRERA MIRTA | F31: 32109890 | G31: 3865642319 | H31: CONCEPCIÓN | I31: [32236] TV 32" ENOVA SMART FULL HD NETFLIX YOUTUBE GOOGLE TV | J31: 33 SEMANAS (33 de $17.600) | K31: $ 17.600 | L31: $580.800 | M31: RAMALLO CARLOS | N31: 32235460 | P31: Clienta activa | Q31: =IF(N31="", "", IF(COUNTIF(F:F, N31)>0, "⚠️ ERROR: YA ES TITULAR", ""))
A32: 46015.688 | B32: BALTIERRA DANIEL | C32: BELÉN | D32: CARPANCHAY MICHELLE JENIFER | F32: 42991977 | G32: 3838414174 | H32: PUNTILLA | I32: [30728] CORTADORA DE FIAMBRE MORETTI TRECENTO PRO 300MM | J32: 48 SEMANAS (48 de $45.000) (ESPECIAL/OFERTA) | K32: CONDICIÓN: CUOTA PURA | L32: $2.160.000 | M32: DELGADO CARLOS ALBERTO | N32: 42376161 | P32: Pasando el río a 25mtsr | Q32: =IF(N32="", "", IF(COUNTIF(F:F, N32)>0, "⚠️ ERROR: YA ES TITULAR", ""))
A33: 46015.834 | B33: ARIAS JENNIFER | C33: CONCEPCIÓN | D33: ROMAN MEDINA AGUSTÍN | F33: 45060925 | G33: 3865513947 | H33: CONCEPCIÓN | I33: A DEFINIR | J33: 24 SEMANAS (24 de $118.500) (ESPECIAL/OFERTA) | K33: $ 2.844.000 | L33: $2.844.000 | M33: NORMA BEATRIZ RAMIRES | N33: 22397155 | Q33: =IF(N33="", "", IF(COUNTIF(F:F, N33)>0, "⚠️ ERROR: YA ES TITULAR", ""))
A34: 46017.535 | B34: SARMIENTO JONATHAN | C34: CATAMARCA | D34: ALDO TEJEDA | F34: 24309665 | G34: 3834404903 | H34: VALLE VIEJO | I34: [31973] LAVARROPAS SEMIAUTOMATICO PATRIK DE 7KG | J34: 24 SEMANAS (24 de $38.900) | K34: $ 38.900 | L34: $933.600 | M34: CRISTIAN CASTRO | N34: 27351221 | Q34: =IF(N34="", "", IF(COUNTIF(F:F, N34)>0, "⚠️ ERROR: YA ES TITULAR", ""))
A35: 46017.548 | B35: JOHN D | C35: SUR CATAMARCA | D35: MANSILLA EDGARDO ANDRÉS | F35: 39807273 | G35: 3834332424 | H35: CAPITAL | I35: [31335] VITRINA EXPOSITORA FAM 520LTS 198CM X 71.5CM | J35: 48 SEMANAS (48 de $60.200) | K35: $ 60.200 | L35: $2.889.600 | M35: GONZÁLEZ RITA MARIELA | N35: 24743263 | Q35: =IF(N35="", "", IF(COUNTIF(F:F, N35)>0, "⚠️ ERROR: YA ES TITULAR", ""))
A36: 46017.68 | B36: ARIAS JENNIFER | C36: CONCEPCIÓN | D36: MEDINAS CARLOS NAZARENO | F36: 34160197 | G36: 2984932363 | H36: CONCEPCIÓN | I36: [32223] CELULAR REDMI 15C CON 16RAM Y 256GB | J36: 33 SEMANAS (33 de $19.800) | K36: $ 19.800 | L36: $653.400 | M36: PRICILA MALENA MACKOW | N36: 45669634 | Q36: =IF(N36="", "", IF(COUNTIF(F:F, N36)>0, "⚠️ ERROR: YA ES TITULAR", ""))
A37: 46017.807 | B37: SEBASTIAN | C37: CATAMARCA | D37: AVELLANEDA PATRICIA AZUCENA | F37: 31648530 | G37: 3834298998 | H37: CATAMARCA | I37: [32201] COLCHON ESPUMA MAXIKING ZAFIRO DE 2 1/2 30CM | J37: 33 SEMANAS (33 de $18.900) | K37: $ 18.900 | L37: $623.700 | M37: AVELLANEDA VALERIA | N37: 32415478 | Q37: =IF(N37="", "", IF(COUNTIF(F:F, N37)>0, "⚠️ ERROR: YA ES TITULAR", ""))
A38: 46017.85 | B38: SEBASTIAN | C38: AGUILARES | D38: VEGA SILVIA ANDREA FABIANA | F38: 22719761 | G38: 3865435009 | H38: AGUILARES | I38: [32153] CELULAR REDMI 14C DE 16RAM Y 256GB DE MEMORIA | J38: 42 SEMANAS (42 de $14.200) | K38: $ 14.200 | L38: $596.400 | M38: ACEVEDO JUAN | N38: 25302373 | Q38: =IF(N38="", "", IF(COUNTIF(F:F, N38)>0, "⚠️ ERROR: YA ES TITULAR", ""))
A39: 46018.442 | B39: DANIEL BALTIERRA | C39: BELÉN | D39: DELGADO MELISA DEL VALLE | F39: 35565481 | G39: 3838471710 | H39: LA PUNTILLA | I39: [30103] RALLADORA DE PAN ELECTRICA DE 10 KG.- MS | J39: 12 SEMANAS (12 de $63.900) | K39: $ 63.900 | L39: $766.800 | M39: VILLAFAÑES JOSÉ | N39: 30311541 | P39: Antes de pasar el rio | Q39: =IF(N39="", "", IF(COUNTIF(F:F, N39)>0, "⚠️ ERROR: YA ES TITULAR", ""))
A40: 46018.491 | B40: ARIAS JENNIFER | C40: CONCEPCIÓN | D40: ALVAREZ GABRIELA ALEJANDRA | F40: 21330334 | G40: 3865418594 | H40: CONCEPCIÓN | I40: [31487] CELULAR SAMSUNG A06 128GB 4RAM | J40: 33 SEMANAS (33 de $19.800) | K40: $ 19.800 | L40: $653.400 | M40: SOFIA FERNÁNDEZ | N40: 33817620 | P40: Horario comercial | Q40: =IF(N40="", "", IF(COUNTIF(F:F, N40)>0, "⚠️ ERROR: YA ES TITULAR", ""))
A41: 46018.675 | B41: JOHN D | C41: SUR CATAMARCA | D41: ARGAÑARAZ MIGUEL EDUARDO | F41: 26187787 | G41: 3834236537 | H41: CAPITAL | I41: [500] EXHIBIDOR MULTIUSO 8 CANASTOS | J41: 33 SEMANAS (33 de $15.200) | K41: $ 15.200 | L41: $501.600 | Q41: =IF(N41="", "", IF(COUNTIF(F:F, N41)>0, "⚠️ ERROR: YA ES TITULAR", ""))
A42: 46018.676 | B42: JOHN D | C42: SUR CATAMARCA | D42: ARGAÑARAZ MIGUEL EDUARDO | F42: 26187787 | G42: 38342365 | I42: [500] EXHIBIDOR MULTIUSO 8 CANASTOS | J42: 33 SEMANAS (33 de $15.200) | K42: $ 15.200 | L42: $501.600 | Q42: =IF(N42="", "", IF(COUNTIF(F:F, N42)>0, "⚠️ ERROR: YA ES TITULAR", ""))
A43: 46018.679 | B43: JOHN D | C43: SUR CATAMARCA | D43: ARGAÑARAZ MIGUEL EDUARDO | F43: 26187787 | G43: 3834236537 | H43: CAPITAL | I43: [500] EXHIBIDOR MULTIUSO 8 CANASTOS | J43: 33 SEMANAS (33 de $15.200) | K43: $ 15.200 | L43: $501.600 | M43: CASTILLO MARÍA SOLEDAD | N43: 26856252 | Q43: =IF(N43="", "", IF(COUNTIF(F:F, N43)>0, "⚠️ ERROR: YA ES TITULAR", ""))
A44: 46018.696 | B44: JOHN D | C44: SUR CATAMARCA | D44: PASTORISA MARÍA DANIELA | F44: 32457069 | G44: 3834265915 | H44: CAPITAL | I44: [32177] LOMITERA CON CARLITERA DEPAOLO DE 60X80 | J44: 33 SEMANAS (33 de $37.600) | K44: $ 37.600 | L44: $1.240.800 | M44: VEGA PASTORISA NAZARENA | N44: 48397632 | Q44: =IF(N44="", "", IF(COUNTIF(F:F, N44)>0, "⚠️ ERROR: YA ES TITULAR", ""))
A45: 46020.481 | B45: ARRIETA GUILLERMO | C45: TINOGASTA | D45: USQUEDA ADRIAN | F45: 40749301 | G45: 3837438423 | H45: TINOGASTA | I45: [603] GONDOLAS CENTRAL 1.60 TRAMO INICIAL MYD SIN PORTA PRECIOS [604] GONDOLAS CENTRAL 1.60 TRAMO ADICIONAL SIN PORTA PRECIOS [30020] GONDOLA PUNTERA 1.60MTS. SIN PORTA PRECIO | J45: 48 SEMANAS (48 de $26.300) 48 SEMANAS (48 de $24.000) 48 SEMANAS (48 de $16.100) | K45: $ 66.400 | L45: $1.262.400 $1.152.000 $772.800 | M45: USQUEDA SILVANA | N45: 26259126 | P45: Horario comercial | Q45: =IF(N45="", "", IF(COUNTIF(F:F, N45)>0, "⚠️ ERROR: YA ES TITULAR", ""))
A46: 46020.494 | B46: NELSON | C46: ZONA SUR | D46: QUINTEROS ALBA | F46: 22219828 | G46: 3834293420 | H46: MIRAFLORES | I46: [30982] HELADERA CON FREEZER ELECTROLUX 420LTS NO FROST C/ DISPENSER | J46: 12 SEMANAS (12 de $148.100) | K46: $ 148.100 | L46: $1.777.200 | M46: LUCERO NAYLA | N46: 43191715 | Q46: =IF(N46="", "", IF(COUNTIF(F:F, N46)>0, "⚠️ ERROR: YA ES TITULAR", ""))
A47: 46020.574 | B47: ARRIETA GUILLERMO | C47: TINOGASTA | D47: LAZCANO BEATRIZ | F47: 36792121 | G47: 3837499440 | H47: FIAMBALA | I47: [32182] HORNO PIZZERO 6 MOLDES DANDA MULTIPLE CON ANAFE Y PLANCHA | J47: 48 SEMANAS (48 de $32.800) | K47: $ 32.800 | L47: $1.574.400 | M47: REALES HUMBERTO JAVIER | N47: 31382609 | P47: Cliente 9285 | Q47: =IF(N47="", "", IF(COUNTIF(F:F, N47)>0, "⚠️ ERROR: YA ES TITULAR", ""))
A48: 46020.682 | B48: RACHID | C48: TACO RALO | D48: MANZILLA MARIANA | F48: 38719472 | G48: 3858538780 | H48: TERMAS | I48: [1] BALANZA ELECTRONICA KRETZ NOVEL ECO2 30KG C/BAT CONTADORA | J48: 42 SEMANAS (42 de $15.800) | K48: $ 15.800 | L48: $663.600 | M48: JUAREZ GONZALO | N48: 38719782 | Q48: =IF(N48="", "", IF(COUNTIF(F:F, N48)>0, "⚠️ ERROR: YA ES TITULAR", ""))
A49: 46020.694 | B49: JOHN DENET | C49: ZONA SUR | D49: MARTINEZ ELIO DAVID | F49: 45457571 | G49: 3834693280 | H49: CAPITAL | I49: [15] COMBO DE PRODUCTOS [31213] PLACARD 6 PUERTAS 2 CAJONES FERRO MUEBLES-C/CEDRO [30297] JUEGO DE COMEDOR SALUMA 1.80X80+6 SILLAS IMPERIAL/RESP/ALTO | J49: 36 SEMANAS (36 de $45.500) (ESPECIAL/OFERTA) 0 SEMANAS (0 de $0) (ESPECIAL/OFERTA) 0 SEMANAS (0 de $0) (ESPECIAL/OFERTA) | K49: $ 45.500 | L49: $1.638.000 $0 $0 | M49: LERA MARÍA NANCY | N49: 18060569 | Q49: =IF(N49="", "", IF(COUNTIF(F:F, N49)>0, "⚠️ ERROR: YA ES TITULAR", ""))
A50: 46020.875 | B50: ARRIETA GUILLERMO | C50: TINOGASTA | D50: PIZARRO SERGIO | F50: 24865678 | G50: 3837436769 | H50: TINOGASTA | I50: [32238] AIRE VENTANA ENOVA FIO SOLO DE 3500W 3000FRIG. | J50: 48 SEMANAS (48 de $37.300) | K50: $ 37.300 | L50: $1.790.400 | M50: LORENA CASAS | N50: 33937456 | P50: Cliente 7543 | Q50: =IF(N50="", "", IF(COUNTIF(F:F, N50)>0, "⚠️ ERROR: YA ES TITULAR", ""))
A51: 46021.402 | B51: NELSON | C51: ZONA SUR | D51: CAHYLE GASTÓN | F51: 39540856 | G51: 3834354711 | H51: CATAMARCA | I51: [30150] PANCHERA MEDIANA TECNOCALOR 24 SALCHICHA | J51: 33 SEMANAS (33 de $24.100) | K51: $ 24.100 | L51: $795.300 | M51: LEGUIZAMON MILAGROS | N51: 44443675 | Q51: =IF(N51="", "", IF(COUNTIF(F:F, N51)>0, "⚠️ ERROR: YA ES TITULAR", ""))
A52: 46021.44 | B52: RAMOS FACUNDO NAHUEL | C52: CONCEPCIÓN | D52: GUERRERO JOSE SEBASTIAN | F52: 33375095 | G52: 3865736305 | H52: CONCEPCIÓN | I52: [30499] VENTILADOR DE PIE CRIVEL 30" V39 INDUSTRIAL | J52: 24 SEMANAS (24 de $17.900) | K52: $ 17.900 | L52: $429.600 | M52: SANDOVAL ROMINA | N52: 34958148 | P52: Panaderia 329 .. | Q52: =IF(N52="", "", IF(COUNTIF(F:F, N52)>0, "⚠️ ERROR: YA ES TITULAR", ""))
A53: 46021.484 | B53: CHAILE | C53: MONTEROS | D53: GRACIAS DAVID | F53: 35029477 | G53: 3863577347 | H53: MONTEROS | I53: [32243] PILETA DE NATACION PELOPINCHO DE 4500LTS 2X3X0,75CM ALTO | J53: 33 SEMANAS (33 de $0) | K53: $ 703.755 | L53: $0 | M53: MARIELA QUINTEROS | N53: 36534479 | Q53: =IF(N53="", "", IF(COUNTIF(F:F, N53)>0, "⚠️ ERROR: YA ES TITULAR", ""))
A54: 46021.484 | B54: CHAILE | C54: MONTEROS | D54: GRACIAS DAVID | F54: 35029477 | G54: 3863577347 | H54: MONTEROS | I54: [32243] PILETA DE NATACION PELOPINCHO DE 4500LTS 2X3X0,75CM ALTO | J54: 33 SEMANAS (33 de $0) | K54: $ 703.755 | L54: $0 | M54: MARIELA QUINTEROS | N54: 36534479 | Q54: =IF(N54="", "", IF(COUNTIF(F:F, N54)>0, "⚠️ ERROR: YA ES TITULAR", ""))
A55: 46021.487 | D55: HABSHS | F55: 62664 | I55: [32243] PILETA DE NATACION PELOPINCHO DE 4500LTS 2X3X0,75CM ALTO | J55: 33 SEMANAS (33 de $19.400) | K55: $ 19.400 | L55: $640.200 | M55: HAHAHS | N55: 15264728 | Q55: =IF(N55="", "", IF(COUNTIF(F:F, N55)>0, "⚠️ ERROR: YA ES TITULAR", ""))
A56: 46021.487 | D56: ASDASD | F56: 123213 | I56: [32243] PILETA DE NATACION PELOPINCHO DE 4500LTS 2X3X0,75CM ALTO | J56: 33 SEMANAS (33 de $19.400) | K56: $ 19.400 | L56: $640.200 | M56: ASDASD | N56: 123123 | Q56: =IF(N56="", "", IF(COUNTIF(F:F, N56)>0, "⚠️ ERROR: YA ES TITULAR", "")) -> ⚠️ ERROR: YA ES TITULAR
A57: 46021.491 | B57: CHAILE | C57: MONTEROS | D57: GARC8A DAVID | F57: 35029477 | G57: 3863577347 | H57: MONTEROS | I57: [32243] PILETA DE NATACION PELOPINCHO DE 4500LTS 2X3X0,75CM ALTO | J57: 33 SEMANAS (33 de $19.400) | K57: $ 19.400 | L57: $640.200 | M57: QUINTEROS MARIELA | N57: 36534479 | Q57: =IF(N57="", "", IF(COUNTIF(F:F, N57)>0, "⚠️ ERROR: YA ES TITULAR", ""))
A58: 46021.5 | B58: BALTIERRA DANIEL | C58: ANDALGALA | D58: 9739- CHIAPPONI GIAN | F58: 35389361 | G58: 3835514109 | H58: SAUJIL | I58: [500] EXHIBIDOR MULTIUSO 8 CANASTOS | J58: 24 SEMANAS (24 de $21.800) | K58: $ 21.800 | L58: $523.200 | M58: MALAGUEÑO JOSÉ FERNANDO | N58: 41015306 | P58: Frente cancha Sportivo saujil | Q58: =IF(N58="", "", IF(COUNTIF(F:F, N58)>0, "⚠️ ERROR: YA ES TITULAR", ""))
A59: 46021.579 | B59: CHAILE | C59: MONTEROS | D59: CASTRO EDUARDO | F59: 32348380 | G59: 3815557111 | H59: SANTA LUCIA | I59: [32238] AIRE VENTANA ENOVA FIO SOLO DE 3500W 3000FRIG. | J59: 48 SEMANAS (48 de $36.100) | K59: $ 36.100 | L59: $1.732.800 | M59: CAMPOS VERÓNICA SOLEDAD | N59: 36654584 | Q59: =IF(N59="", "", IF(COUNTIF(F:F, N59)>0, "⚠️ ERROR: YA ES TITULAR", ""))
A60: 46021.759 | B60: ARIAS JENNIFER | C60: CONCEPCIÓN | D60: MOYANO EMANUEL ERIK | F60: 35519069 | G60: 291533969 | H60: CONCEPCIÓN | I60: [31919] MINICOMPONENTE PARLANTE EVERSOUND EV-363 2000W | J60: 24 SEMANAS (24 de $58.900) | K60: $ 58.900 | L60: $1.413.600 | M60: GUTIERREZ OSCAR | N60: 38585413 | Q60: =IF(N60="", "", IF(COUNTIF(F:F, N60)>0, "⚠️ ERROR: YA ES TITULAR", ""))
A61: 46021.781 | B61: SANTIAGO | C61: TRINIDAD | D61: SANTIAGO | F61: 123345 | I61: [COMBO-15] COMBO (Cód 15): [31335] VITRINA EXPOSITORA FAM 520LTS 198CM X 71.5CM (x1) + [32100] FREEZER HORIZONTAL TEORA 350LTS DUAL (x1) | J61: 36 SEMANAS (36 de $65.000) (ESPECIAL/OFERTA) | K61: $ 65.000 | L61: $2.340.000 | M61: SANTIAGO | N61: 1526383 | Q61: =IF(N61="", "", IF(COUNTIF(F:F, N61)>0, "⚠️ ERROR: YA ES TITULAR", ""))
A62: 46021.855 | B62: RACHID | C62: TACO RALO | D62: MADRID RAQUEL ESTELA DEL VALLE | F62: 14660129 | G62: 3865313300 | H62: TACO RALO | I62: [30982] HELADERA CON FREEZER ELECTROLUX 420LTS NO FROST C/ DISPENSER | J62: 48 SEMANAS (48 de $50.900) | K62: $ 51.000 | L62: $2.443.200 | M62: MADRID MARIA MAGDALENA | N62: 17041983 | Q62: =IF(N62="", "", IF(COUNTIF(F:F, N62)>0, "⚠️ ERROR: YA ES TITULAR", ""))
A63: 46022.449 | B63: ARRIETA GUILLERMO | C63: TINOGASTA | D63: MAMANI BETINA | F63: 37553595 | G63: 3837698161 | H63: FIAMBALA | I63: [30110] FREEZER FAM 310 LTS F_310DG | J63: 46 SEMANAS (46 de $38.000) (ESPECIAL/OFERTA) | K63: $ 38.000 | L63: $1.748.000 | M63: RASGADO LUCAS | N63: 42047934 | P63: Solicitud ya autorizada ,cliente quiere cambiar producto | Q63: =IF(N63="", "", IF(COUNTIF(F:F, N63)>0, "⚠️ ERROR: YA ES TITULAR", ""))
A64: 46022.48 | B64: MIRABAL | C64: LOS VALLES | D64: REYES LUIS | F64: 28416971 | G64: 3838400636 | H64: SANTA MARÍA | I64: [30297] JUEGO DE COMEDOR SALUMA 1.80X80+6 SILLAS IMPERIAL/RESP/ALTO | J64: 24 SEMANAS (24 de $39.200) | K64: $ 39.200 | L64: $940.800 | M64: REYES JESÚS ALBERTO PASCUAL | N64: 39998417 | Q64: =IF(N64="", "", IF(COUNTIF(F:F, N64)>0, "⚠️ ERROR: YA ES TITULAR", ""))
A65: 46022.516 | B65: RUBÉN MAMANI | C65: FAMAILLA | D65: HERRERA IRMA | F65: 5154090 | G65: 3816691398 | H65: FAMAILLA | I65: [31240] MOSTRADOR DE 90X1.85X45 CON ESTANTES Y PUERTAS CORREDIZA | J65: 24 SEMANAS (24 de $26.000) | K65: $ 26.000 | L65: $624.000 | M65: VARGAS CLAUDIA | N65: 24316756 | Q65: =IF(N65="", "", IF(COUNTIF(F:F, N65)>0, "⚠️ ERROR: YA ES TITULAR", ""))
A66: 46024.388 | D66: TERZANO SEBASTIAN | F66: 31543514 | G66: 3865650116 | H66: CONCEPCION | I66: [COMBO-15] COMBO (Cód 15): [31335] VITRINA EXPOSITORA FAM 520LTS 198CM X 71.5CM (x1) + [30110] FREEZER FAM 310 LTS F_310DG (x2) | J66: 50 SEMANAS (50 de $48.000) (ESPECIAL/OFERTA) | K66: $ 48.000 | L66: $2.400.000 | M66: PEREZ JUAN | N66: 12345645 | Q66: =IF(N66="", "", IF(COUNTIF(F:F, N66)>0, "⚠️ ERROR: YA ES TITULAR", ""))
A67: 46024.516 | B67: KEVIN | C67: SANTA ANA | D67: JUDITH CELIA MORENO | F67: 34282362 | G67: 3865297568 | H67: SANTA ANA | I67: [30572] PANCHUQUERA SUPER DE 5 DIVISIONES | J67: 42 SEMANAS (42 de $16.700) | K67: $ 16.700 | L67: $701.400 | M67: MORENO PABLO FRANCISCO | N67: 10940982 | Q67: =IF(N67="", "", IF(COUNTIF(F:F, N67)>0, "⚠️ ERROR: YA ES TITULAR", ""))
A68: 46024.644 | B68: BALTIERRA DANIEL | C68: BELEN | D68: BELLIDO KARINA ALEJANDRA | F68: 35391262 | G68: 3835431887 | H68: LONDRES | I68: A DEFINIR | J68: 46 SEMANAS (46 de $60) (ESPECIAL/OFERTA) | K68: $ 60.000 | L68: $2.760 | M68: BELLIDO RICARDO JAVIER | N68: 37642370 | Q68: =IF(N68="", "", IF(COUNTIF(F:F, N68)>0, "⚠️ ERROR: YA ES TITULAR", ""))
A69: 46024.795 | B69: LUCIANO LANCIONI | C69: CONCEPCIÓN | D69: SEBASTIÁN DIAZ | F69: 34555666 | G69: 3865208615 | H69: CONCEPCION | I69: [32158] VITRINA EXPOSITORA EQUIPADA TEORA 600LTS | J69: 24 SEMANAS (24 de $132.100) | K69: $ 132.100 | L69: $3.170.400 | M69: MARTA JUAREZ | N69: 23455666 | Q69: =IF(N69="", "", IF(COUNTIF(F:F, N69)>0, "⚠️ ERROR: YA ES TITULAR", ""))
A70: 46024.799 | B70: LUCIANO LANCIONI | C70: CONCEPCIÓN | D70: LUCIANO IVAN | F70: 55543777 | G70: 3865208615 | H70: CONCEPCION | I70: [30132] VITRINA EXPOSITORA BAJA TEMPERATURA FAM 420LTS P/CONGELADOS [31033] FREEZER FAM F-1200DG CONDEN. DINAM. 1200LTS GALVANIZADO | J70: 48 SEMANAS (48 de $50.000) (ESPECIAL/OFERTA) 24 SEMANAS (24 de $183.200) | K70: $ 233.200 | L70: $2.400.000 $4.396.800 | M70: GISEL | N70: 65777888 | Q70: =IF(N70="", "", IF(COUNTIF(F:F, N70)>0, "⚠️ ERROR: YA ES TITULAR", ""))
A71: 46024.881 | B71: CHAILE | C71: MONTEROS | D71: RODRIGUEZ RENE ROGELIO | F71: 20968836 | G71: 3863500990 | H71: CAP. CACERES | I71: [32238] AIRE VENTANA ENOVA FIO SOLO DE 3500W 3000FRIG. (x2) | J71: 48 SEMANAS (48 de $72.100) | K71: $ 72.100 | L71: $3.460.800 | M71: RIVADERO MONICA MERCEDEZ | N71: 23546258 | P71: Cliente Inactivo | Q71: =IF(N71="", "", IF(COUNTIF(F:F, N71)>0, "⚠️ ERROR: YA ES TITULAR", ""))
A72: 46025.415 | D72: MONTOYA RICARDO MATIAS | F72: 30841044 | G72: 3812122421 | H72: LULES | I72: [32153] CELULAR REDMI 14C DE 16RAM Y 256GB DE MEMORIA | J72: 33 SEMANAS (33 de $17.000) | K72: $ 17.000 | L72: $561.000 | M72: LESCANO JUAN | N72: 33372939 | Q72: =IF(N72="", "", IF(COUNTIF(F:F, N72)>0, "⚠️ ERROR: YA ES TITULAR", ""))
A73: 46025.42 | D73: GONZALEZ ROSSANA DEL VALLE | F73: 24643333 | G73: 3865659664 | H73: CONCEPCION | I73: [31986] VENTILADOR DE PIE 20" EVESREST A-20 PALA METALICA INDUSTRIAL | J73: 1 SEMANAS (1 de $198.750) (ESPECIAL/OFERTA) | K73: $ 198.750 | L73: $198.750 | P73: Venta con Tarjeta | Q73: =IF(N73="", "", IF(COUNTIF(F:F, N73)>0, "⚠️ ERROR: YA ES TITULAR", ""))
A74: 46025.474 | B74: ULISES | C74: AGUILARES | D74: SALAS MARIO ADRIAN | F74: 24401199 | G74: 3865268550 | H74: AGUILARES | I74: [32223] CELULAR REDMI 15C CON 16RAM Y 256GB (x2) | J74: 42 SEMANAS (42 de $32.600) | K74: $ 32.600 | L74: $1.369.200 | M74: TORTI FERNANDA | N74: 30231326 | Q74: =IF(N74="", "", IF(COUNTIF(F:F, N74)>0, "⚠️ ERROR: YA ES TITULAR", ""))
A75: 46025.476 | B75: MARIANO | C75: AGUILARES | D75: OVEJERO MARIA GRACIELA | F75: 17655144 | G75: 3865230428 | H75: AGUILARES | I75: [603] GONDOLAS CENTRAL 1.60 TRAMO INICIAL MYD SIN PORTA PRECIOS [604] GONDOLAS CENTRAL 1.60 TRAMO ADICIONAL SIN PORTA PRECIOS [32186] HORNO PIZZERO 3 MOLDES DANDA C/ PLANCHA Y CARLITERA MULTIGAS | J75: 42 SEMANAS (42 de $28.600) 42 SEMANAS (42 de $26.100) 24 SEMANAS (24 de $36.600) | K75: $ 91.300 | L75: $1.201.200 $1.096.200 $878.400 | M75: OVEJERO JORGE | N75: 25004666 | Q75: =IF(N75="", "", IF(COUNTIF(F:F, N75)>0, "⚠️ ERROR: YA ES TITULAR", ""))
A76: 46025.713 | B76: SEBASTIAN | C76: CONCEPCION | D76: LEDESMA ALDANA MILENA | F76: 44376903 | G76: 3865717334 | H76: PIEDRA GRANDE | I76: A DEFINIR | J76: 46 SEMANAS (46 de $60.000) (ESPECIAL/OFERTA) | K76: $ 60.000 | L76: $2.760.000 | M76: LEDESMA ESTEFANIA | N76: 45126050 | Q76: =IF(N76="", "", IF(COUNTIF(F:F, N76)>0, "⚠️ ERROR: YA ES TITULAR", ""))
A77: 46025.716 | B77: SEBASTIAN | C77: CONCEPCION | D77: LEDESMA ALDANA MILENA | F77: 44376903 | G77: 3865717334 | H77: PIEDRA GRANDE | I77: [31335] VITRINA EXPOSITORA FAM 520LTS 198CM X 71.5CM | J77: 46 SEMANAS (46 de $60.000) (ESPECIAL/OFERTA) | K77: $ 60.000 | L77: $2.760.000 | M77: LEDESMA ESTEFANIA | N77: 45126050 | P77: Frente la Escuela | Q77: =IF(N77="", "", IF(COUNTIF(F:F, N77)>0, "⚠️ ERROR: YA ES TITULAR", ""))
A78: 46025.757 | B78: IBAÑEZ ENRIQUE | C78: TRINIDAD | D78: COSTILLA AYELEN ESTEFANÍA | F78: 43652316 | G78: 3865343099 | H78: MEDINAS | I78: [32236] TV 32" ENOVA SMART FULL HD NETFLIX YOUTUBE GOOGLE TV | J78: 24 SEMANAS (24 de $24.100) | K78: $ 24.100 | L78: $578.400 | M78: DIAZ ÁNGEL ORLANDO | N78: 16687584 | P78: Comienza a pagar pero no recibirá aún | Q78: =IF(N78="", "", IF(COUNTIF(F:F, N78)>0, "⚠️ ERROR: YA ES TITULAR", ""))
A79: 46025.956 | B79: NELSON | C79: ZONA SUR | D79: MAZA MARCIA MARIBEL | F79: 33049175 | G79: 3834035463 | H79: CATAMARCA | I79: [32223] CELULAR REDMI 15C CON 16RAM Y 256GB | J79: 33 SEMANAS (33 de $20.000) | K79: $ 20.000 | L79: $660.000 | M79: MAZA LUIS ALBERTO | N79: 11366919 | Q79: =IF(N79="", "", IF(COUNTIF(F:F, N79)>0, "⚠️ ERROR: YA ES TITULAR", ""))
A80: 46025.964 | B80: JOHN D | C80: SUR CATAMARCA | D80: MARTINEZ ELIO DAVID | F80: 45457571 | G80: 3834693280 | H80: CAPITAL | I80: [30131] LAVARROPAS AUTOMATICO DREAN 10KG INVERTER CARGA FRONTAL | J80: 48 SEMANAS (48 de $48.900) | K80: $ 48.900 | L80: $2.347.200 | M80: LERA MARÍA NANCY | N80: 18060569 | Q80: =IF(N80="", "", IF(COUNTIF(F:F, N80)>0, "⚠️ ERROR: YA ES TITULAR", ""))
A81: 46026.475 | B81: MARIANO | C81: AGUILARES | D81: OVEJERO MARIA GRACIELA | F81: 17655144 | G81: 3865230428 | H81: AGUILARES | I81: [32214] HORNO PIZZERO 6 MOLDES DANDA C/PLANCHA Y CARLITERA MULTIGAS | J81: 12 SEMANAS (12 de $86.300) | K81: $ 86.300 | L81: $1.035.600 | M81: OVEJERO JORGE | N81: 25004666 | P81: Cliente autorizado, cambio de producto | Q81: =IF(N81="", "", IF(COUNTIF(F:F, N81)>0, "⚠️ ERROR: YA ES TITULAR", ""))
A82: 46026.573 | B82: ELSA | C82: SUR | D82: MUZZILLO MARIO ALBERTO | F82: 32282401 | G82: 3834242403 | H82: CATAMARCA | I82: [30728] CORTADORA DE FIAMBRE MORETTI TRECENTO PRO 300MM | J82: 48 SEMANAS (48 de $45.000) (ESPECIAL/OFERTA) | K82: $ 45.000 | L82: $2.160.000 | M82: SILVA DÉBORA JUDITH | N82: 36348430 | P82: Entre Argentino de Oro y Peso Fuerte | Q82: =IF(N82="", "", IF(COUNTIF(F:F, N82)>0, "⚠️ ERROR: YA ES TITULAR", ""))
A83: 46026.943 | B83: BALTIERRA DANIEL | C83: BELÉN | D83: OCHOA BRENDA GISEL | F83: 39999138 | G83: 3835509048 | H83: BELÉN | I83: [30384] AIRE ACONDICIONADO SPLIT BGH 3450W F/SOLO BS35WFC 3000F | J83: 36 SEMANAS (36 de $45.000) (ESPECIAL/OFERTA) | K83: $ 45.000 | L83: $1.620.000 | M83: VILLACORTA JONATAN GABRIEL | N83: 41223761 | Q83: =IF(N83="", "", IF(COUNTIF(F:F, N83)>0, "⚠️ ERROR: YA ES TITULAR", ""))
A84: 46027.307 | B84: VAZQUEZ | C84: NORTE | D84: SILVA MARIA DE LOS ANGELES | F84: 43191395 | G84: 3834743253 | H84: CATAMARCA | I84: [32088] HORNO PIZZERO 6 MOLDES DANDA MULTIGAS C/LADRILLOS REF. | J84: 24 SEMANAS (24 de $31.100) | K84: $ 31.100 | L84: $746.400 | M84: GARAY BEATRIZ DEL CARMEN | N84: 26856320 | Q84: =IF(N84="", "", IF(COUNTIF(F:F, N84)>0, "⚠️ ERROR: YA ES TITULAR", ""))
A85: 46027.372 | B85: ELSA | C85: CATAMARCA | D85: VILLACORTA DIEGO FERNANDO | F85: 26729367 | G85: 3834712949 | H85: CATAMARCA | I85: [31658] REBOZADORA DE MILANESA Z5.PARA 50KG DE CARNE POR HORA | J85: 42 SEMANAS (42 de $50.600) | K85: $ 50.600 | L85: $2.125.200 | M85: VILLACORTA ENZO RAUL | N85: 30088183 | Q85: =IF(N85="", "", IF(COUNTIF(F:F, N85)>0, "⚠️ ERROR: YA ES TITULAR", ""))
A86: 46027.444 | B86: VAZQUEZ | C86: NORTE | D86: YGNACIO YAMILA GIMENA | F86: 37089903 | G86: 3834270834 | H86: CAPITAL | I86: [30728] CORTADORA DE FIAMBRE MORETTI TRECENTO PRO 300MM | J86: 42 SEMANAS (42 de $51.800) | K86: $ 51.800 | L86: $2.175.600 | M86: YGNACIO YANINA TAMARA | N86: 39997113 | Q86: =IF(N86="", "", IF(COUNTIF(F:F, N86)>0, "⚠️ ERROR: YA ES TITULAR", ""))
A87: 46027.458 | B87: ELSA | C87: CATAMARCA | D87: VILLEGRA LUCIANA MABEL | F87: 29369493 | G87: 3834627780 | H87: VALLE VIEJO | I87: [31503] COCINA INDUSTRIAL 4 HORNALLA C/PLANCHA Y CARLITERA TECNOCALO | J87: 33 SEMANAS (33 de $57.300) | K87: $ 57.300 | L87: $1.890.900 | M87: BRANDAN DIEGO | N87: 25928726 | Q87: =IF(N87="", "", IF(COUNTIF(F:F, N87)>0, "⚠️ ERROR: YA ES TITULAR", ""))
A88: 46027.56 | B88: ARIAS JENNIFER | C88: CONCEPCIÓN | D88: JULIAN MURCANI | F88: 22556281 | G88: 3816648713 | H88: CONCEPCIÓN | I88: [32123] CONSERVADORA PARA HELADOS FAM22 INOXIDABLE (12+10 )BALDES | J88: CONTADO ($1.401.500) | K88: $ 1.401.500 | L88: $1.401.500 | Q88: =IF(N88="", "", IF(COUNTIF(F:F, N88)>0, "⚠️ ERROR: YA ES TITULAR", ""))
A89: 46027.634 | B89: NELSON | C89: ZONA SUR | D89: OLEA MICAELA (9492) | F89: 40434092 | G89: 3834300146 | H89: CATAMARCA | I89: [30103] RALLADORA DE PAN ELECTRICA DE 10 KG.- MS | J89: 12 SEMANAS (12 de $61.800) | K89: $ 61.800 | L89: $741.600 | M89: PÉREZ HEBER RAÚL | N89: 36348082 | Q89: =IF(N89="", "", IF(COUNTIF(F:F, N89)>0, "⚠️ ERROR: YA ES TITULAR", ""))
A90: 46027.638 | B90: NELSON | C90: ZONA SUR | D90: GONZÁLEZ GUADALUPE MARIA CELESTE | F90: 41844356 | G90: 3834940094 | H90: CATAMARCA | I90: [32100] FREEZER HORIZONTAL TEORA 350LTS DUAL | J90: 48 SEMANAS (48 de $39.700) | K90: $ 39.700 | L90: $1.905.600 | M90: MAMANI LEANDRO JOEL | N90: 39540154 | Q90: =IF(N90="", "", IF(COUNTIF(F:F, N90)>0, "⚠️ ERROR: YA ES TITULAR", ""))
A91: 46027.67 | B91: KEVIN | C91: AGUILARES | D91: RODRÍGUEZ DEOLINDA YOANA ELIZABETH | F91: 34867167 | G91: 3865657216 | H91: AGUILARES | I91: [31565] FREEZER HORIZONTAL NEBA 400LTS 1 TAPA | J91: 44 SEMANAS (44 de $43.000) (ESPECIAL/OFERTA) | K91: CONDICIÓN: CUOTA PURA | L91: $1.892.000 | M91: PERALTA JUAN PEDRO | N91: 22556378 | Q91: =IF(N91="", "", IF(COUNTIF(F:F, N91)>0, "⚠️ ERROR: YA ES TITULAR", ""))
A92: 46027.737 | B92: JUAN | C92: MONTEROS | D92: CARLOS DANTE ALE | F92: 17892543 | G92: 3863432411 | H92: MONTEROS | I92: [31912] MUEBLES DE 15 CUBOS MDF DE 1MTSX.45CMX1.85MTS | J92: 33 SEMANAS (33 de $20.500) | K92: $ 20.500 | L92: $676.500 | M92: SILVIA ROXANA MEDINA | N92: 22895712 | Q92: =IF(N92="", "", IF(COUNTIF(F:F, N92)>0, "⚠️ ERROR: YA ES TITULAR", ""))
A93: 46027.76 | B93: SEBASTIAN | C93: AGUILARES | D93: CARRIZO SANTIAGO MAURO | F93: 40356158 | G93: 3812465783 | H93: AGUILARES | I93: [30110] FREEZER FAM 310 LTS F_310DG | J93: 46 SEMANAS (46 de $38.000) (ESPECIAL/OFERTA) | K93: $ 38.000 | L93: $1.748.000 | M93: SORIA SABINA | N93: 42549211 | Q93: =IF(N93="", "", IF(COUNTIF(F:F, N93)>0, "⚠️ ERROR: YA ES TITULAR", ""))
A94: 46027.789 | B94: CHAILE | C94: FAMAILLA | D94: ALE CONSTANZA MAILEN | F94: 43502382 | G94: 3814095924 | H94: FAMAILLA | I94: [31206] ZORRA HIDRAULICA TRASPAPELETA MANUAL PARA 2500KG | J94: 12 SEMANAS (12 de $66.200) | K94: $ 66.200 | L94: $794.400 | M94: DIAZ ENZO NICOLAS | N94: 37091545 | P94: Cliente inactivo | Q94: =IF(N94="", "", IF(COUNTIF(F:F, N94)>0, "⚠️ ERROR: YA ES TITULAR", ""))
A95: 46027.794 | B95: CHAILE | C95: FAMAILLA | D95: MUÑOZ LUIS GABRIEL | F95: 26076964 | G95: 3814487323 | H95: STA LUCIA | I95: [32047] BATIDORA PEABODY CON BOWL DE 4LT DE 1000W | J95: 33 SEMANAS (33 de $16.100) | K95: $ 16.100 | L95: $531.300 | M95: MUÑOZ LUIS ALBERTO | N95: 40086822 | Q95: =IF(N95="", "", IF(COUNTIF(F:F, N95)>0, "⚠️ ERROR: YA ES TITULAR", ""))
A96: 46027.798 | B96: ELSA | C96: CATAMARCA | D96: VILLAGRA LUCIANA MABEL | F96: 29369493 | G96: 3834627780 | H96: VALLE VIEJO | I96: [32135] COCINA SEMI INDUSTRIAL DEPAOLO 2 H CON PLANCHA Y CARLITERA | J96: 33 SEMANAS (33 de $30.500) | K96: $ 30.500 | L96: $1.006.500 | M96: BRANDAN DIEGO | N96: 25928726 | Q96: =IF(N96="", "", IF(COUNTIF(F:F, N96)>0, "⚠️ ERROR: YA ES TITULAR", ""))
A97: 46027.847 | B97: KEVIN PEREZ | C97: AGUILARES | D97: NAHUEL LEONARDO ISAÍAS SORAIRE | F97: 35150885 | G97: 3865748002 | H97: AGUILARES | I97: [32234] AIRE ACONDICIONADO SPLIT RCA 3200W DE 2800FRIG. F/C | J97: 48 SEMANAS (48 de $33.600) | K97: CONDICIÓN: CUOTA PURA | L97: $1.612.800 | M97: FLAVIA VANESA RODRÍGUEZ | N97: 35150885 | Q97: =IF(N97="", "", IF(COUNTIF(F:F, N97)>0, "⚠️ ERROR: YA ES TITULAR", "")) -> ⚠️ ERROR: YA ES TITULAR
A98: 46027.871 | D98: ANCE ROBERTO NICOLAS | F98: 30767269 | G98: 3865204386 | H98: CONCEPCIÓN | I98: [32010] PILETA DE NATACION PELOPINCHO DE 8000LTS 4.50X2.25X80ALTO | J98: 33 SEMANAS (33 de $14.700) | K98: $ 14.700 | L98: $485.100 | M98: ROBLEDO DEOLINDA YANINA | N98: 35519092 | P98: Cerca puente viejo ruta 38 | Q98: =IF(N98="", "", IF(COUNTIF(F:F, N98)>0, "⚠️ ERROR: YA ES TITULAR", ""))
A99: 46028.37 | B99: NELSON | C99: ZONA NORTE | D99: CARIVA RAMÓN SILVESTRE | F99: 36844700 | G99: 3834058601 | H99: CATAMARCA | I99: [31987] HELADERA CON FREEZER DREAN 364 LTS BLANCA | J99: 48 SEMANAS (48 de $61.600) | K99: $ 61.600 | L99: $2.956.800 | M99: SÁBADOS ISABEL BARROS | N99: 22186938 | Q99: =IF(N99="", "", IF(COUNTIF(F:F, N99)>0, "⚠️ ERROR: YA ES TITULAR", ""))
A100: 46028.38 | B100: SEBASTIAN | C100: CONCEPCION | D100: CARRIZO MARIANA DE LOS ANGELES | F100: 39574143 | G100: 3865244589 | H100: CONCEPCION | I100: [32231] TV 43" ENOVA SMART FULL HD NETFLIX YOUTUBE GOOGLE TV | J100: 33 SEMANAS (33 de $27.400) | K100: $ 27.400 | L100: $904.200 | M100: GONZALEZ MARCOS | N100: 39574097 | P100: Anres de llegar a la Sarratea | Q100: =IF(N100="", "", IF(COUNTIF(F:F, N100)>0, "⚠️ ERROR: YA ES TITULAR", ""))
...

Sheet Hoja 3
A1: =Registro!A1 -> FECHA | B1: =Registro!B1 -> VENDEDOR | C1: =Registro!C1 -> ZONA | D1: =Registro!D1 -> CLIENTE | E1: =Registro!F1 -> DNI | F1: =Registro!G1 -> TELEFONO | G1: =Registro!H1 -> LOCALIDAD | H1: =Registro!I1 -> PRODUCTOS | I1: =Registro!J1 -> PLANES | J1: =Registro!K1 -> ANTICIPO | K1: =Registro!L1 -> TOTAL | L1: =Registro!M1 -> CONYUGUE | M1: =Registro!N1 -> DNI CONYUGUE | N1: =Registro!P1 -> OBSERVACIONES
A2: =Registro!A2 -> 46010.852 | B2: =Registro!B2 -> SEBASTIAN | C2: =Registro!C2 -> CATAMARCA | D2: =Registro!D2 -> LUJAN MARIA LAURA | E2: =Registro!F2 -> 34783489 | F2: =Registro!G2 -> 3834190133 | G2: =Registro!H2 -> CATAMARCA | H2: =Registro!I2 -> [31335] VITRINA EXPOSITORA FAM 520LTS 198CM X 71.5CM | I2: =Registro!J2 -> 46 SEMANAS (46 de $60.000) (ESPECIAL/OFERTA) | J2: =Registro!K2 -> $ 60.000 | K2: =Registro!L2 -> $2.760.000 | L2: =Registro!M2 -> PACHECO MIGUEL | M2: =Registro!N2 -> 32698148 | N2: =Registro!P2 | O2: =IF(M2="", "", IF(COUNTIF(E:E, M2)>0, "⚠️ ERROR: YA ES TITULAR", ""))
A3: =Registro!A3 -> 46011.419 | B3: =Registro!B3 -> RACHID TURBAY | C3: =Registro!C3 -> LOS ALTOS | D3: =Registro!D3 -> GUARAZ JUAN CARLOS | E3: =Registro!F3 -> 20714826 | F3: =Registro!G3 -> 3834517687 | G3: =Registro!H3 -> BAÑADO DE OVANTA | H3: =Registro!I3 -> [31835] CONSERVADORA PARA HELADOS FAM 220LTS TAPA DE CRISTAL CURVO | I3: =Registro!J3 -> 33 SEMANAS (33 de $44.000) (ESPECIAL/OFERTA) | J3: =Registro!K3 -> $ 44.000 | K3: =Registro!L3 -> $1.452.000 | L3: =Registro!M3 -> COLLANTE LUCIANA | M3: =Registro!N3 -> 29104369 | N3: =Registro!P3 -> Venta por cambio. | O3: =IF(M3="", "", IF(COUNTIF(E:E, M3)>0, "⚠️ ERROR: YA ES TITULAR", ""))
A4: =Registro!A4 -> 46011.488 | B4: =Registro!B4 -> ARIAS JENNIFER | C4: =Registro!C4 -> CONCEPCIÓN | D4: =Registro!D4 -> FIGUEROA HUMBERTO | E4: =Registro!F4 -> 27141564 | F4: =Registro!G4 -> 3865672557 | G4: =Registro!H4 -> CONCEPCIÓN | H4: =Registro!I4 -> [30500] VENTILADOR DE PARED CRIVEL 30" V40 INDUSTRIAL | I4: =Registro!J4 -> 12 SEMANAS (12 de $25.600) | J4: =Registro!K4 -> $ 25.600 | K4: =Registro!L4 -> $307.200 | L4: =Registro!M4 -> ANA LIA ALBORADO | M4: =Registro!N4 -> 31312339 | N4: =Registro!P4 -> Esta a partir de las 10 a 15 | O4: =IF(M4="", "", IF(COUNTIF(E:E, M4)>0, "⚠️ ERROR: YA ES TITULAR", ""))
A5: =Registro!A5 -> 46011.498 | B5: =Registro!B5 -> SOLANA | C5: =Registro!C5 -> CATAMARCA | D5: =Registro!D5 -> BRIZUELA CRISTINA ALILIA | E5: =Registro!F5 -> 22219976 | F5: =Registro!G5 -> 3834303788 | G5: =Registro!H5 -> CATAMARCA | H5: =Registro!I5 -> [32215] SOMMIER MAXIKIG DE 2 1/2 ESPUMA 30CM ZAFIRO | I5: =Registro!J5 -> CONTADO ($572.300) | J5: =Registro!K5 -> $ 572.300 | K5: =Registro!L5 -> $572.300 | L5: =Registro!M5 | M5: =Registro!N5 | N5: =Registro!P5 | O5: =IF(M5="", "", IF(COUNTIF(E:E, M5)>0, "⚠️ ERROR: YA ES TITULAR", ""))
A6: =Registro!A6 -> 46011.622 | B6: =Registro!B6 -> JOHN | C6: =Registro!C6 -> SUR CATAMARCA | D6: =Registro!D6 -> CARRIZO FABIANA MARISEL | E6: =Registro!F6 -> 32851577 | F6: =Registro!G6 -> 3834012088 | G6: =Registro!H6 -> CAPITAL CATAMARCA | H6: =Registro!I6 -> [32223] CELULAR REDMI 15C CON 16RAM Y 256GB | I6: =Registro!J6 -> 24 SEMANAS (24 de $26.600) | J6: =Registro!K6 -> $ 26.600 | K6: =Registro!L6 -> $638.400 | L6: =Registro!M6 -> MORALES JUAN ADRIAN | M6: =Registro!N6 -> 34187127 | N6: =Registro!P6 -> Polleria Noah | O6: =IF(M6="", "", IF(COUNTIF(E:E, M6)>0, "⚠️ ERROR: YA ES TITULAR", ""))
A7: =Registro!A7 -> 46011.835 | B7: =Registro!B7 -> RACHID | C7: =Registro!C7 -> ALBERDI | D7: =Registro!D7 -> BRIZUELA VALENTINA | E7: =Registro!F7 -> 45669557 | F7: =Registro!G7 -> 3814189518 | G7: =Registro!H7 -> ALBERDI | H7: =Registro!I7 -> [31580] SIERRA CARNICERA MOD.320 MONOFASICA 2HP MESADA DE AC. INX. | I7: =Registro!J7 -> 33 SEMANAS (33 de $137.900) | J7: =Registro!K7 -> $ 137.900 | K7: =Registro!L7 -> $4.550.700 | L7: =Registro!M7 -> ALBARRACIN ISAIAS | M7: =Registro!N7 -> 45125190 | N7: =Registro!P7 | O7: =IF(M7="", "", IF(COUNTIF(E:E, M7)>0, "⚠️ ERROR: YA ES TITULAR", ""))
A8: =Registro!A8 -> 46012.962 | B8: =Registro!B8 -> JUAN MONTEROS | C8: =Registro!C8 -> CONCEPCIÓN | D8: =Registro!D8 -> CEJAS ESTER | E8: =Registro!F8 -> 18300841 | F8: =Registro!G8 -> 3865290520 | G8: =Registro!H8 -> ALTO VERDE | H8: =Registro!I8 -> [31948] LICUADORA LITIUM 1.5LTS VASO VIDRIO/500W/ 5 VEL /PICA HIELO | I8: =Registro!J8 -> 6 SEMANAS (6 de $25.000) (ESPECIAL/OFERTA) | J8: =Registro!K8 -> $ 25.000 | K8: =Registro!L8 -> $150.000 | L8: =Registro!M8 -> CEJAS JOEL | M8: =Registro!N8 -> 42717595 | N8: =Registro!P8 | O8: =IF(M8="", "", IF(COUNTIF(E:E, M8)>0, "⚠️ ERROR: YA ES TITULAR", ""))
A9: =Registro!A9 -> 46013.38 | B9: =Registro!B9 -> RUBEN | C9: =Registro!C9 -> FAMAILLA | D9: =Registro!D9 -> RUBÉN MAMANI | E9: =Registro!F9 -> 29048976 | F9: =Registro!G9 -> 3815112636 | G9: =Registro!H9 -> FAMAILLA | H9: =Registro!I9 -> [32011] AIRE ACONDICIONADO SPLIT ALASKA 3550W DE 3000 FRIG. F/CALOR | I9: =Registro!J9 -> 33 SEMANAS (33 de $64.600) | J9: =Registro!K9 -> $ 64.600 | K9: =Registro!L9 -> $2.131.800 | L9: =Registro!M9 -> CASTRO JULIA | M9: =Registro!N9 -> 31770372 | N9: =Registro!P9 -> Horario comercial 8 a 14 | O9: =IF(M9="", "", IF(COUNTIF(E:E, M9)>0, "⚠️ ERROR: YA ES TITULAR", ""))
A10: =Registro!A10 -> 46013.41 | B10: =Registro!B10 -> FRANCO | C10: =Registro!C10 -> MOLLAR-TAFI | D10: =Registro!D10 -> GRIMALT KAREN LUCIA | E10: =Registro!F10 -> 40028787 | F10: =Registro!G10 -> 3815620884 | G10: =Registro!H10 -> TAFI DEL VALLE | H10: =Registro!I10 -> [31912] MUEBLES DE 15 CUBOS MDF DE 1MTSX.45CMX1.85MTS | I10: =Registro!J10 -> 33 SEMANAS (33 de $21.200) | J10: =Registro!K10 -> $ 21.200 | K10: =Registro!L10 -> $699.600 | L10: =Registro!M10 -> CEQUEIRA FACUNDO ADRIAN | M10: =Registro!N10 -> 41184528 | N10: =Registro!P10 | O10: =IF(M10="", "", IF(COUNTIF(E:E, M10)>0, "⚠️ ERROR: YA ES TITULAR", ""))
A11: =Registro!A11 -> 46013.426 | B11: =Registro!B11 -> CHAILE | C11: =Registro!C11 -> MONTEROS | D11: =Registro!D11 -> JOSÉ JAVIER GOMEZ | E11: =Registro!F11 -> 41447476 | F11: =Registro!G11 -> 3812109862 | G11: =Registro!H11 -> BELLA VISTA | H11: =Registro!I11 -> [31719] MOSTRADOR MULTIFUNCION MT 1.50MTS X 0.45CM MDF CAR. Y CAJON | I11: =Registro!J11 -> 33 SEMANAS (33 de $21.300) | J11: =Registro!K11 -> $ 21.300 | K11: =Registro!L11 -> $702.900 | L11: =Registro!M11 -> LORENA PAOLA JUAREZ | M11: =Registro!N11 -> 40086992 | N11: =Registro!P11 | O11: =IF(M11="", "", IF(COUNTIF(E:E, M11)>0, "⚠️ ERROR: YA ES TITULAR", ""))
A12: =Registro!A12 -> 46013.496 | B12: =Registro!B12 -> ELSA | C12: =Registro!C12 -> SUR | D12: =Registro!D12 -> BRUNELLO, VALENTINA | E12: =Registro!F12 -> 44117256 | F12: =Registro!G12 -> 3834594447 | G12: =Registro!H12 -> VALLE CHICO | H12: =Registro!I12 -> [32024] HORNO PIZZERO CATANIA 6M PUERTA DE VIDRIO C/CALIENTA PLATOS | I12: =Registro!J12 -> 24 SEMANAS (24 de $49.100) | J12: =Registro!K12 -> $ 49.100 | K12: =Registro!L12 -> $1.178.400 | L12: =Registro!M12 -> BRANCIA, CINTIA | M12: =Registro!N12 -> 34777837 | N12: =Registro!P12 | O12: =IF(M12="", "", IF(COUNTIF(E:E, M12)>0, "⚠️ ERROR: YA ES TITULAR", ""))
A13: =Registro!A13 -> 46013.503 | B13: =Registro!B13 -> ELSA | C13: =Registro!C13 -> CATAMARCA | D13: =Registro!D13 -> GUZMAN, SANDRA DEL VALLE | E13: =Registro!F13 -> 18060901 | F13: =Registro!G13 -> 3834380773 | G13: =Registro!H13 -> CATAMARCA | H13: =Registro!I13 -> [302] HORNO PIZZERO TECNOCALOR 12 MOLDES AC/INOX GE INDUSTRIAL | I13: =Registro!J13 -> 33 SEMANAS (33 de $47.000) | J13: =Registro!K13 -> $ 47.000 | K13: =Registro!L13 -> $1.551.000 | L13: =Registro!M13 -> FERREYRA VERONICA YANEL | M13: =Registro!N13 -> 36844813 | N13: =Registro!P13 | O13: =IF(M13="", "", IF(COUNTIF(E:E, M13)>0, "⚠️ ERROR: YA ES TITULAR", ""))
... A22: =Registro!A22 -> 46014.437 | B22: =Registro!B22 -> RUBÉN MAMANI | C22: =Registro!C22 -> LULES | D22: =Registro!D22 -> CHINCHA EUGENIA | E22: =Registro!F22 -> 92614054 | F22: =Registro!G22 -> 3815605991 | G22: =Registro!H22 -> LULES (MERCED) | H22: =Registro!I22 -> [31237] VITRINA DOBLE MT 1.85MTS X 0.90 X 0.45CM MDF C/PUERTAS | I22: =Registro!J22 -> 24 SEMANAS (24 de $25.800) | J22: =Registro!K22 -> $ 25.800 | K22: =Registro!L22 -> $619.200 | L22: =Registro!M22 -> CHINCHA MARIVEL | M22: =Registro!N22 -> 92760508 | N22: =Registro!P22 -> Av roca 1000 | O22: =IF(M22="", "", IF(COUNTIF(E:E, M22)>0, "⚠️ ERROR: YA ES TITULAR", ""))
A23: =Registro!A536 | B23: =Registro!B536 | C23: =Registro!C536 | D23: =Registro!D536 | E23: =Registro!F536 | F23: =Registro!G536 | G23: =Registro!H536 | H23: =Registro!I536 | I23: =Registro!J536 | J23: =Registro!K536 | K23: =Registro!L536 | L23: =Registro!M536 | M23: =Registro!N536 | N23: =Registro!P536 | O23: =IF(M23="", "", IF(COUNTIF(E:E, M23)>0, "⚠️ ERROR: YA ES TITULAR", ""))
A24: =Registro!A537 | B24: =Registro!B537 | C24: =Registro!C537 | D24: =Registro!D537 | E24: =Registro!F537 | F24: =Registro!G537 | G24: =Registro!H537 | H24: =Registro!I537 | I24: =Registro!J537 | J24: =Registro!K537 | K24: =Registro!L537 | L24: =Registro!M537 | M24: =Registro!N537 | N24: =Registro!P537 | O24: =IF(M24="", "", IF(COUNTIF(E:E, M24)>0, "⚠️ ERROR: YA ES TITULAR", ""))
A25: =Registro!A538 | B25: =Registro!B538 | C25: =Registro!C538 | D25: =Registro!D538 | E25: =Registro!F538 | F25: =Registro!G538 | G25: =Registro!H538 | H25: =Registro!I538 | I25: =Registro!J538 | J25: =Registro!K538 | K25: =Registro!L538 | L25: =Registro!M538 | M25: =Registro!N538 | N25: =Registro!P538 | O25: =IF(M25="", "", IF(COUNTIF(E:E, M25)>0, "⚠️ ERROR: YA ES TITULAR", ""))
A26: =Registro!A539 | B26: =Registro!B539 | C26: =Registro!C539 | D26: =Registro!D539 | E26: =Registro!F539 | F26: =Registro!G539 | G26: =Registro!H539 | H26: =Registro!I539 | I26: =Registro!J539 | J26: =Registro!K539 | K26: =Registro!L539 | L26: =Registro!M539 | M26: =Registro!N539 | N26: =Registro!P539 | O26: =IF(M26="", "", IF(COUNTIF(E:E, M26)>0, "⚠️ ERROR: YA ES TITULAR", ""))
A27: =Registro!A540 | B27: =Registro!B540 | C27: =Registro!C540 | D27: =Registro!D540 | E27: =Registro!F540 | F27: =Registro!G540 | G27: =Registro!H540 | H27: =Registro!I540 | I27: =Registro!J540 | J27: =Registro!K540 | K27: =Registro!L540 | L27: =Registro!M540 | M27: =Registro!N540 | N27: =Registro!P540 | O27: =IF(M27="", "", IF(COUNTIF(E:E, M27)>0, "⚠️ ERROR: YA ES TITULAR", ""))
A28: =Registro!A541 | B28: =Registro!B541 | C28: =Registro!C541 | D28: =Registro!D541 | E28: =Registro!F541 | F28: =Registro!G541 | G28: =Registro!H541 | H28: =Registro!I541 | I28: =Registro!J541 | J28: =Registro!K541 | K28: =Registro!L541 | L28: =Registro!M541 | M28: =Registro!N541 | N28: =Registro!P541 | O28: =IF(M28="", "", IF(COUNTIF(E:E, M28)>0, "⚠️ ERROR: YA ES TITULAR", ""))
A29: =Registro!A542 | B29: =Registro!B542 | C29: =Registro!C542 | D29: =Registro!D542 | E29: =Registro!F542 | F29: =Registro!G542 | G29: =Registro!H542 | H29: =Registro!I542 | I29: =Registro!J542 | J29: =Registro!K542 | K29: =Registro!L542 | L29: =Registro!M542 | M29: =Registro!N542 | N29: =Registro!P542 | O29: =IF(M29="", "", IF(COUNTIF(E:E, M29)>0, "⚠️ ERROR: YA ES TITULAR", ""))
A30: =Registro!A543 | B30: =Registro!B543 | C30: =Registro!C543 | D30: =Registro!D543 | E30: =Registro!F543 | F30: =Registro!G543 | G30: =Registro!H543 | H30: =Registro!I543 | I30: =Registro!J543 | J30: =Registro!K543 | K30: =Registro!L543 | L30: =Registro!M543 | M30: =Registro!N543 | N30: =Registro!P543 | O30: =IF(M30="", "", IF(COUNTIF(E:E, M30)>0, "⚠️ ERROR: YA ES TITULAR", ""))
A31: =Registro!A544 | B31: =Registro!B544 | C31: =Registro!C544 | D31: =Registro!D544 | E31: =Registro!F544 | F31: =Registro!G544 | G31: =Registro!H544 | H31: =Registro!I544 | I31: =Registro!J544 | J31: =Registro!K544 | K31: =Registro!L544 | L31: =Registro!M544 | M31: =Registro!N544 | N31: =Registro!P544 | O31: =IF(M31="", "", IF(COUNTIF(E:E, M31)>0, "⚠️ ERROR: YA ES TITULAR", ""))
A32: =Registro!A545 | B32: =Registro!B545 | C32: =Registro!C545 | D32: =Registro!D545 | E32: =Registro!F545 | F32: =Registro!G545 | G32: =Registro!H545 | H32: =Registro!I545 | I32: =Registro!J545 | J32: =Registro!K545 | K32: =Registro!L545 | L32: =Registro!M545 | M32: =Registro!N545 | N32: =Registro!P545 | O32: =IF(M32="", "", IF(COUNTIF(E:E, M32)>0, "⚠️ ERROR: YA ES TITULAR", ""))
A33: =Registro!A546 | B33: =Registro!B546 | C33: =Registro!C546 | D33: =Registro!D546 | E33: =Registro!F546 | F33: =Registro!G546 | G33: =Registro!H546 | H33: =Registro!I546 | I33: =Registro!J546 | J33: =Registro!K546 | K33: =Registro!L546 | L33: =Registro!M546 | M33: =Registro!N546 | N33: =Registro!P546 | O33: =IF(M33="", "", IF(COUNTIF(E:E, M33)>0, "⚠️ ERROR: YA ES TITULAR", ""))
A34: =Registro!A547 | B34: =Registro!B547 | C34: =Registro!C547 | D34: =Registro!D547 | E34: =Registro!F547 | F34: =Registro!G547 | G34: =Registro!H547 | H34: =Registro!I547 | I34: =Registro!J547 | J34: =Registro!K547 | K34: =Registro!L547 | L34: =Registro!M547 | M34: =Registro!N547 | N34: =Registro!P547 | O34: =IF(M34="", "", IF(COUNTIF(E:E, M34)>0, "⚠️ ERROR: YA ES TITULAR", ""))
... A549: =Registro!A1062 | B549: =Registro!B1062 | C549: =Registro!C1062 | D549: =Registro!D1062 | E549: =Registro!F1062 | F549: =Registro!G1062 | G549: =Registro!H1062 | H549: =Registro!I1062 | I549: =Registro!J1062 | J549: =Registro!K1062 | K549: =Registro!L1062 | L549: =Registro!M1062 | M549: =Registro!N1062 | N549: =Registro!P1062 | O549: =IF(M549="", "", IF(COUNTIF(E:E, M549)>0, "⚠️ ERROR: YA ES TITULAR", ""))
A550: =Registro!A1063 | B550: =Registro!B1063 | C550: =Registro!C1063 | D550: =Registro!D1063 | E550: =Registro!F1063 | F550: =Registro!G1063 | G550: =Registro!H1063 | H550: =Registro!I1063 | I550: =Registro!J1063 | J550: =Registro!K1063 | K550: =Registro!L1063 | L550: =Registro!M1063 | M550: =Registro!N1063 | N550: =Registro!P1063
A551: =Registro!A1064 | B551: =Registro!B1064 | C551: =Registro!C1064 | D551: =Registro!D1064 | E551: =Registro!F1064 | F551: =Registro!G1064 | G551: =Registro!H1064 | H551: =Registro!I1064 | I551: =Registro!J1064 | J551: =Registro!K1064 | K551: =Registro!L1064 | L551: =Registro!M1064 | M551: =Registro!N1064 | N551: =Registro!P1064
A552: =Registro!A1065 | B552: =Registro!B1065 | C552: =Registro!C1065 | D552: =Registro!D1065 | E552: =Registro!F1065 | F552: =Registro!G1065 | G552: =Registro!H1065 | H552: =Registro!I1065 | I552: =Registro!J1065 | J552: =Registro!K1065 | K552: =Registro!L1065 | L552: =Registro!M1065 | M552: =Registro!N1065 | N552: =Registro!P1065
A553: =Registro!A1066 | B553: =Registro!B1066 | C553: =Registro!C1066 | D553: =Registro!D1066 | E553: =Registro!F1066 | F553: =Registro!G1066 | G553: =Registro!H1066 | H553: =Registro!I1066 | I553: =Registro!J1066 | J553: =Registro!K1066 | K553: =Registro!L1066 | L553: =Registro!M1066 | M553: =Registro!N1066 | N553: =Registro!P1066
A554: =Registro!A1067 | B554: =Registro!B1067 | C554: =Registro!C1067 | D554: =Registro!D1067 | E554: =Registro!F1067 | F554: =Registro!G1067 | G554: =Registro!H1067 | H554: =Registro!I1067 | I554: =Registro!J1067 | J554: =Registro!K1067 | K554: =Registro!L1067 | L554: =Registro!M1067 | M554: =Registro!N1067 | N554: =Registro!P1067
A555: =Registro!A1068 | B555: =Registro!B1068 | C555: =Registro!C1068 | D555: =Registro!D1068 | E555: =Registro!F1068 | F555: =Registro!G1068 | G555: =Registro!H1068 | H555: =Registro!I1068 | I555: =Registro!J1068 | J555: =Registro!K1068 | K555: =Registro!L1068 | L555: =Registro!M1068 | M555: =Registro!N1068 | N555: =Registro!P1068
A556: =Registro!A1069 | B556: =Registro!B1069 | C556: =Registro!C1069 | D556: =Registro!D1069 | E556: =Registro!F1069 | F556: =Registro!G1069 | G556: =Registro!H1069 | H556: =Registro!I1069 | I556: =Registro!J1069 | J556: =Registro!K1069 | K556: =Registro!L1069 | L556: =Registro!M1069 | M556: =Registro!N1069 | N556: =Registro!P1069
A557: =Registro!A1070 | B557: =Registro!B1070 | C557: =Registro!C1070 | D557: =Registro!D1070 | E557: =Registro!F1070 | F557: =Registro!G1070 | G557: =Registro!H1070 | H557: =Registro!I1070 | I557: =Registro!J1070 | J557: =Registro!K1070 | K557: =Registro!L1070 | L557: =Registro!M1070 | M557: =Registro!N1070 | N557: =Registro!P1070
A558: =Registro!A1071 | B558: =Registro!B1071 | C558: =Registro!C1071 | D558: =Registro!D1071 | E558: =Registro!F1071 | F558: =Registro!G1071 | G558: =Registro!H1071 | H558: =Registro!I1071 | I558: =Registro!J1071 | J558: =Registro!K1071 | K558: =Registro!L1071 | L558: =Registro!M1071 | M558: =Registro!N1071 | N558: =Registro!P1071
A559: =Registro!A1072 | B559: =Registro!B1072 | C559: =Registro!C1072 | D559: =Registro!D1072 | E559: =Registro!F1072 | F559: =Registro!G1072 | G559: =Registro!H1072 | H559: =Registro!I1072 | I559: =Registro!J1072 | J559: =Registro!K1072 | K559: =Registro!L1072 | L559: =Registro!M1072 | M559: =Registro!N1072 | N559: =Registro!P1072
A560: =Registro!A1073 | B560: =Registro!B1073 | C560: =Registro!C1073 | D560: =Registro!D1073 | E560: =Registro!F1073 | F560: =Registro!G1073 | G560: =Registro!H1073 | H560: =Registro!I1073 | I560: =Registro!J1073 | J560: =Registro!K1073 | K560: =Registro!L1073 | L560: =Registro!M1073 | M560: =Registro!N1073 | N560: =Registro!P1073
A561: =Registro!A1074 | B561: =Registro!B1074 | C561: =Registro!C1074 | D561: =Registro!D1074 | E561: =Registro!F1074 | F561: =Registro!G1074 | G561: =Registro!H1074 | H561: =Registro!I1074 | I561: =Registro!J1074 | J561: =Registro!K1074 | K561: =Registro!L1074 | L561: =Registro!M1074 | M561: =Registro!N1074 | N561: =Registro!P1074
... A978: =Registro!A1491 | B978: =Registro!B1491 | C978: =Registro!C1491 | D978: =Registro!D1491 | E978: =Registro!F1491 | F978: =Registro!G1491 | G978: =Registro!H1491 | H978: =Registro!I1491 | I978: =Registro!J1491 | J978: =Registro!K1491 | K978: =Registro!L1491 | L978: =Registro!M1491 | M978: =Registro!N1491 | N978: =Registro!P1491
